README.md
setup.py
CardGames.egg-info/PKG-INFO
CardGames.egg-info/SOURCES.txt
CardGames.egg-info/dependency_links.txt
CardGames.egg-info/requires.txt
CardGames.egg-info/top_level.txt
cards/__init__.py
cards/classification_utils.py
cards/classify_hand.py
cards/deck.py
cards/exceptions.py
cards/five_card_hand.py
cards/playing_cards.py
cards/poker_hands.py
cards/ranks.py
cards/suits.py
holdem/__init__.py
holdem/board.py
holdem/dealer.py
holdem/exceptions.py
tests/test_cards/__init__.py
tests/test_cards/test_cards.py
tests/test_cards/test_deck.py
tests/test_cards/test_poker_hands.py
tests/test_cards/test_rank.py
tests/test_cards/test_suits.py
tests/test_holdem/__init__.py
tests/test_holdem/test_board.py
tests/test_holdem/test_dealer.py