Metadata-Version: 1.0
Name: CardGames
Version: 0.0.0
Summary: Various tools and scripts for card games.
Home-page: https://github.com/exzacktlee/CardGames
Author: Zachary Lee
Author-email: zach3lee@gmail.com
License: UNKNOWN
Keywords: cards games
Platform: UNKNOWN
